[
  {
    "_id": "5e5b973544ae6a86546a8979",
    "name": "Toning Lotion Normal/Dry Skin",
    "brand": "Clarins",
    "images": {
      "url": "http://192.168.1.181:8080/products/5e5b973544ae6a86546a8979.gif"
    },
    "size": {
      "amount": 400,
      "unit": "ml"
    },
    "prices": [
      {
        "price": 100,
        "website": "5e5b8e15999899821c5f71fa"
      },
      {
        "price": 120,
        "website": "5e58383cf6eea26b079e590c"
      },
      {
        "price": 98,
        "website": "5e58383cf6eea26b079e590b"
      },
      {
        "price": 80,
        "website": "5e58383cf6eea26b079e590e"
      }
    ]
  },
  {
    "_id": "5e5b973544ae6a86546a897a",
    "brand": "Exuviance",
    "name": "SkinRise Bionic Tonic",
    "images": {
      "url": "http://192.168.1.181:8080/products/5e5b973544ae6a86546a897a.gif"
    },
    "size": {
      "amount": 60,
      "unit": "ml"
    },
    "prices": [
      {
        "price": 100,
        "website": "5e58383cf6eea26b079e591a"
      },
      {
        "price": 120,
        "website": "5e58383cf6eea26b079e591b"
      }
    ]
  },
  {
    "_id": "5e5b973544ae6a86546a8989",
    "brand": "Moroccanoil",
    "name": "Moroccanoil Original Oil Treatment",
    "images": {
      "url": "http://192.168.1.181:8080/products/5e5b973544ae6a86546a8989.gif"
    },
    "size": {
      "amount": 100,
      "unit": "ml"
    },
    "prices": [
      {
        "price": 349,
        "website": "5e5b8e15999899821c5f71f5"
      },
      {
        "price": 289,
        "website": "5e58383cf6eea26b079e5908"
      },
      {
        "price": 230,
        "website": "5e58383cf6eea26b079e5903"
      },
      {
        "price": 318,
        "website": "5e58383cf6eea26b079e5901"
      }
    ]
  },
  {
    "_id": "5e5b973544ae6a86546a8988",
    "brand": "Löwengrip",
    "name": "Long Lasting Shampoo",
    "images": {
      "url": "http://192.168.1.181:8080/products/5e5b973544ae6a86546a8988.gif"
    },
    "size": {
      "amount": 250,
      "unit": "ml"
    },
    "prices": [
      {
        "price": 116,
        "website": "5e5b8e15999899821c5f71f5"
      },
      {
        "price": 120,
        "website": "5e58383cf6eea26b079e5908"
      },
      {
        "price": 290,
        "website": "5e58383cf6eea26b079e5903"
      },
      {
        "price": 101,
        "website": "5e58383cf6eea26b079e5901"
      }
    ]
  },
  {
    "_id": "5e5b973544ae6a86546a8978",
    "brand": "Tan-Luxe",
    "name": "The Gradual Illuminating Tanning Lotion",
    "images": {
      "url": "http://192.168.1.181:8080/products/5e5b973544ae6a86546a8978.gif"
    },
    "size": {
      "amount": 250,
      "unit": "ml"
    },
    "prices": [
      {
        "price": 274,
        "website": "5e5b8e15999899821c5f71f5"
      },
      {
        "price": 305,
        "website": "5e58383cf6eea26b079e5908"
      },
      {
        "price": 240,
        "website": "5e58383cf6eea26b079e5903"
      },
      {
        "price": 323,
        "website": "5e58383cf6eea26b079e5901"
      }
    ]
  }
]