[
  {
    "_id": "5e58383cf6eea26b079e790d",
    "name": "Åhlens",
    "website": "https://www.ahlens.se",
    "images": {
      "url": "http://192.168.1.181:8080/webshop/5e58383cf6eea26b079e790d.png"
    },
    "rating": 4.1
  },
  {
    "_id": "5e58383cf6eea26b079e791d",
    "name": "Parfym.se",
    "website": "https://www.parfym.se",
    "images": {
      "url": "http://192.168.1.181:8080/webshop/5e58383cf6eea26b079e791d.png"
    },
    "rating": 4.6
  },
  {
    "_id": "5e58383cf6eea26b079e792d",
    "name": "Daystyle.se",
    "website": "https://daystyle.se",
    "images": {
      "url": "http://192.168.1.181:8080/webshop/5e58383cf6eea26b079e792d-small.png"
    },
    "rating": 3.2
  },
  {
    "_id": "5e58383cf6eea26b079e793d",
    "name": "Skincity",
    "website": "https://skincity.se",
    "images": {
      "url": "http://192.168.1.181:8080/webshop/5e58383cf6eea26b079e793d-medium.png"
    },
    "rating": null
  },
  {
    "_id": "5e58383cf6eea26b079e794d",
    "name": "Kicks",
    "website": "https://www.kicks.se/",
    "images": {
      "url": "http://192.168.1.181:8080/webshop/5e58383cf6eea26b079e794d-medium.png"
    },
    "rating": 4.3
  }
]